ican/__init__.py
ican/base.py
ican/cli.py
ican/color.py
ican/config.py
ican/emojis.py
ican/exceptions.py
ican/git.py
ican/ican.py
ican/log.py
ican/pipeline.py
ican/source.py
ican/version.py
ican-0.2.2.dist-info/LICENSE
ican-0.2.2.dist-info/METADATA
ican-0.2.2.dist-info/WHEEL
ican-0.2.2.dist-info/entry_points.txt
ican-0.2.2.dist-info/top_level.txt
ican-0.2.2.dist-info/RECORD
