Metadata-Version: 2.1
Name: ican
Version: 0.2.2
Summary: ican is a simple version bumper/build pipeline orchestrator
License: MIT
Project-URL: Homepage, https://github.com/jthop/ican
Project-URL: Bug Tracker, https://github.com/jthop/ican/issues
Keywords: api,auth
Classifier: Development Status :: 5 - Production/Stable
Classifier: Natural Language :: English
Classifier: Intended Audience :: Developers
Classifier: Operating System :: OS Independent
Classifier: License :: OSI Approved :: MIT License
Classifier: Environment :: Console
Classifier: Topic :: Software Development :: Version Control
License-File: LICENSE
Requires-Dist: importlib-metadata ; python_version < "3.11"
